mcp_server_email/__init__.py
mcp_server_email/__main__.py
mcp_server_email/email.json
mcp_server_email/server.py
mcp_server_email-0.1.6.dist-info/METADATA
mcp_server_email-0.1.6.dist-info/WHEEL
mcp_server_email-0.1.6.dist-info/entry_points.txt
mcp_server_email-0.1.6.dist-info/licenses/LICENSE
mcp_server_email-0.1.6.dist-info/RECORD
