Metadata-Version: 2.4
Name: mcp-server-email
Version: 0.1.6
Summary: A Model Context Protocol server for email
Author-email: Tian Ming Guang <2593666979@qq.com>
License: MIT
License-File: LICENSE
Keywords: email,llm,math,mcp
Classifier: Development Status :: 4 - Beta
Classifier: Intended Audience :: Developers
Classifier: License :: OSI Approved :: MIT License
Classifier: Programming Language :: Python :: 3
Classifier: Programming Language :: Python :: 3.10
Requires-Python: >=3.10
Requires-Dist: mcp>=1.4.1
Requires-Dist: pydantic>=2.0.0
Requires-Dist: python-dotenv>=1.0.1
